complexity/__init__.py
complexity/core/__init__.py
complexity/core/attention.py
complexity/core/dynamics.py
complexity/core/layer.py
complexity/core/mlp.py
complexity/core/normalization.py
complexity/core/rotary.py
complexity/core/token_routed_mlp.py
complexity/cuda/__init__.py
complexity/cuda/fused_attention.py
complexity/cuda/fused_mlp.py
complexity/cuda/fused_residual.py
complexity/cuda/optimized_layer.py
complexity/cuda/persistent_cggr.py
complexity/cuda/quantization.py
complexity/cuda/triton_token_routed.py
complexity/models/__init__.py
complexity/models/config.py
complexity/models/modeling.py
complexity/models/utils.py
complexity/robotics/__init__.py
complexity/robotics/inference.py
complexity/robotics/model.py
complexity/robotics/simulation.py
complexity/robotics/tokenizer.py
complexity_model-0.8.3.dist-info/METADATA
complexity_model-0.8.3.dist-info/WHEEL
complexity_model-0.8.3.dist-info/top_level.txt
complexity_model-0.8.3.dist-info/RECORD
