Metadata-Version: 2.4
Name: complexity-model
Version: 0.8.3
Summary: Complexity transformer with SimplifiedPID dynamics, Mu-Guided Attention/MLP, and Token-Routed MLP
Home-page: https://github.com/Web3-League/complexity-model
Author: Pacific-Prime
Author-email: 
Project-URL: GitHub, https://github.com/Web3-League/complexity-model
Keywords: llm transformer token-routed-mlp flash-attention qk-norm complexity cggr triton robotics cuda
Classifier: Development Status :: 4 - Beta
Classifier: Intended Audience :: Developers
Classifier: Intended Audience :: Science/Research
Classifier: License :: OSI Approved :: MIT License
Classifier: Programming Language :: Python :: 3
Classifier: Programming Language :: Python :: 3.8
Classifier: Programming Language :: Python :: 3.9
Classifier: Programming Language :: Python :: 3.10
Classifier: Programming Language :: Python :: 3.11
Classifier: Programming Language :: Python :: 3.12
Classifier: Topic :: Scientific/Engineering :: Artificial Intelligence
Requires-Python: >=3.8
Requires-Dist: torch>=2.0.0
Requires-Dist: transformers>=4.30.0
Requires-Dist: tokenizers>=0.13.0
Provides-Extra: training
Requires-Dist: datasets>=2.0.0; extra == "training"
Requires-Dist: tensorboard; extra == "training"
Requires-Dist: tqdm; extra == "training"
Provides-Extra: cuda
Requires-Dist: triton>=2.0.0; extra == "cuda"
Provides-Extra: robotics
Requires-Dist: numpy; extra == "robotics"
Requires-Dist: mujoco; extra == "robotics"
Provides-Extra: all
Requires-Dist: triton>=2.0.0; extra == "all"
Requires-Dist: datasets>=2.0.0; extra == "all"
Requires-Dist: tensorboard; extra == "all"
Requires-Dist: tqdm; extra == "all"
Requires-Dist: numpy; extra == "all"
Requires-Dist: mujoco; extra == "all"
Provides-Extra: dev
Requires-Dist: pytest; extra == "dev"
Requires-Dist: black; extra == "dev"
Requires-Dist: isort; extra == "dev"
Dynamic: author
Dynamic: classifier
Dynamic: description
Dynamic: description-content-type
Dynamic: home-page
Dynamic: keywords
Dynamic: project-url
Dynamic: provides-extra
Dynamic: requires-dist
Dynamic: requires-python
Dynamic: summary
